LICENSE.md
MANIFEST.in
README.md
pyproject.toml
setup.py
version.txt
amici/CMakeLists.txt
amici/MANIFEST.template.in
amici/__init__.py
amici/__init__.template.py
amici/__main__.py
amici/antimony_import.py
amici/bngl_import.py
amici/compile.py
amici/conserved_quantities_demartino.py
amici/conserved_quantities_rref.py
amici/constants.py
amici/custom_commands.py
amici/cxxcodeprinter.py
amici/de_export.py
amici/de_model.py
amici/de_model_components.py
amici/git_version.txt
amici/gradient_check.py
amici/import_utils.py
amici/logging.py
amici/numpy.py
amici/pandas.py
amici/plotting.py
amici/pysb_import.py
amici/sbml_import.py
amici/sbml_utils.py
amici/setup.template.py
amici/splines.py
amici/swig.py
amici/swig_wrappers.py
amici/sympy_utils.py
amici/version.txt
amici.egg-info/PKG-INFO
amici.egg-info/SOURCES.txt
amici.egg-info/dependency_links.txt
amici.egg-info/entry_points.txt
amici.egg-info/requires.txt
amici.egg-info/top_level.txt
amici/ThirdParty/SuiteSparse/.gitattributes
amici/ThirdParty/SuiteSparse/.gitignore
amici/ThirdParty/SuiteSparse/CITATION.bib
amici/ThirdParty/SuiteSparse/CMakeLists.txt
amici/ThirdParty/SuiteSparse/CONTRIBUTING.md
amici/ThirdParty/SuiteSparse/ChangeLog
amici/ThirdParty/SuiteSparse/LICENSE.txt
amici/ThirdParty/SuiteSparse/README.md
amici/ThirdParty/SuiteSparse/AMD/CMakeLists.txt
amici/ThirdParty/SuiteSparse/AMD/Makefile
amici/ThirdParty/SuiteSparse/AMD/README.txt
amici/ThirdParty/SuiteSparse/AMD/Config/AMD.pc.in
amici/ThirdParty/SuiteSparse/AMD/Config/AMDConfig.cmake.in
amici/ThirdParty/SuiteSparse/AMD/Config/amd.h.in
amici/ThirdParty/SuiteSparse/AMD/Config/amd_version.tex.in
amici/ThirdParty/SuiteSparse/AMD/Doc/AMD_UserGuide.bib
amici/ThirdParty/SuiteSparse/AMD/Doc/AMD_UserGuide.tex
amici/ThirdParty/SuiteSparse/AMD/Doc/ChangeLog
amici/ThirdParty/SuiteSparse/AMD/Doc/License.txt
amici/ThirdParty/SuiteSparse/AMD/Doc/Makefile
amici/ThirdParty/SuiteSparse/AMD/Doc/amd_version.tex
amici/ThirdParty/SuiteSparse/AMD/Include/amd.h
amici/ThirdParty/SuiteSparse/AMD/Include/amd_internal.h
amici/ThirdParty/SuiteSparse/AMD/Source/amd_1.c
amici/ThirdParty/SuiteSparse/AMD/Source/amd_2.c
