Metadata-Version: 2.4
Name: amici
Version: 0.34.2
Summary: Advanced multi-language Interface to CVODES and IDAS
Author: Jan Hasenauer, AMICI contributors
Author-email: Fabian Froehlich <froehlichfab@gmail.com>, Daniel Weindl <sci@danielweindl.de>
Maintainer-email: Fabian Froehlich <froehlichfab@gmail.com>, Daniel Weindl <sci@danielweindl.de>
License-Expression: BSD-3-Clause
Project-URL: Homepage, https://github.com/AMICI-dev/AMICI
Project-URL: Documentation, https://amici.readthedocs.io/en/latest/
Project-URL: Repository, https://github.com/AMICI-dev/AMICI.git
Project-URL: Bug Tracker, https://github.com/AMICI-dev/AMICI/issues
Keywords: differential equations,simulation,ode,cvodes,systems biology,sensitivity analysis,sbml,pysb,petab
Classifier: Development Status :: 5 - Production/Stable
Classifier: Intended Audience :: Science/Research
Classifier: Operating System :: POSIX :: Linux
Classifier: Operating System :: MacOS :: MacOS X
Classifier: Programming Language :: Python
Classifier: Programming Language :: C++
Classifier: Topic :: Scientific/Engineering :: Bio-Informatics
Requires-Python: >=3.11
License-File: LICENSE.md
Requires-Dist: cmake-build-extension==0.6.0
Requires-Dist: sympy>=1.12.1
Requires-Dist: numpy>=1.23.2; python_version == "3.11"
Requires-Dist: numpy>=1.26.2; python_version == "3.12"
Requires-Dist: numpy; python_version >= "3.13"
Requires-Dist: python-libsbml
Requires-Dist: pandas>=2.0.2
Requires-Dist: pyarrow
Requires-Dist: sbmlmath>=0.4.0
Requires-Dist: toposort
Requires-Dist: setuptools>=48
Requires-Dist: mpmath
Requires-Dist: swig
Provides-Extra: petab
Requires-Dist: petab>=0.4.0; extra == "petab"
Provides-Extra: pysb
Requires-Dist: pysb>=1.13.1; extra == "pysb"
Provides-Extra: test
Requires-Dist: h5py; extra == "test"
Requires-Dist: pytest; extra == "test"
Requires-Dist: pytest-cov; extra == "test"
Requires-Dist: pytest-rerunfailures; extra == "test"
Requires-Dist: coverage; extra == "test"
Requires-Dist: shyaml; extra == "test"
Requires-Dist: antimony>=2.13; extra == "test"
Requires-Dist: antimony!=2.14; (platform_system == "Darwin" and platform_machine in "x86_64h") and extra == "test"
Requires-Dist: scipy; extra == "test"
Requires-Dist: pooch; extra == "test"
Requires-Dist: beartype; extra == "test"
Provides-Extra: vis
Requires-Dist: matplotlib; extra == "vis"
Requires-Dist: seaborn; extra == "vis"
Provides-Extra: examples
Requires-Dist: jupyter; extra == "examples"
Requires-Dist: scipy; extra == "examples"
Provides-Extra: jax
Requires-Dist: jax>=0.4.36; extra == "jax"
Requires-Dist: jaxlib>=0.4.36; extra == "jax"
Requires-Dist: diffrax>=0.7.0; extra == "jax"
Requires-Dist: jaxtyping>=0.2.34; extra == "jax"
Requires-Dist: equinox>=0.11.10; extra == "jax"
Requires-Dist: optimistix>=0.0.9; extra == "jax"
Requires-Dist: interpax<=0.3.6,>=0.3.3; extra == "jax"
Dynamic: license-file
